nonebot_plugin_heisi/__init__.py
nonebot_plugin_heisi-0.3.1.dist-info/LICENSE
nonebot_plugin_heisi-0.3.1.dist-info/METADATA
nonebot_plugin_heisi-0.3.1.dist-info/WHEEL
nonebot_plugin_heisi-0.3.1.dist-info/top_level.txt
nonebot_plugin_heisi-0.3.1.dist-info/RECORD
