Metadata-Version: 2.1
Name: nonebot-plugin-heisi
Version: 0.3.1
Summary: nonebot2 plugin heisi
Home-page: https://github.com/yzyyz1387/nonebot_plugin_heisi
Author: yzyyz1387
Author-email: youzyyz1384@qq.com
License: UNKNOWN
Keywords: pip,nonebot2,nonebot,heisi,nonebot_plugin
Platform: any
Classifier: Programming Language :: Python :: 3
Classifier: License :: OSI Approved :: MIT License
Classifier: Operating System :: OS Independent
License-File: LICENSE
Requires-Dist: httpx
Requires-Dist: nonebot-adapter-onebot (>=2.0.0-beta.1)
Requires-Dist: nonebot2 (>=2.0.0-beta.1)
